{
  "api_version": "1.0.0",
  "authors": [
    {
      "avatar_url": "https://avatars.githubusercontent.com/u/220904984?v=4",
      "name": "merlushkaa",
      "url": "https://github.com/merlushkaa"
    },
    {
      "avatar_url": "",
      "name": "merlusha",
      "url": ""
    }
  ],
  "categories": [],
  "created_at": 1776333227,
  "dependencies": [],
  "description": "EN\nMerluAIguard 🛡️\n\nMerluAIguard is a cutting-edge anti-cheat system for Minecraft Bedrock (Lumi Core/Nukkit), leveraging deep learning (LSTM neural networks) to analyze player behavior in real-time.\n🚀 Key Features\n\n    Deep Learning Analysis: Utilizes a 3-layer LSTM neural network to detect complex cheat patterns.\n\n    Real-time Detection: Processes 40-tick sequences for precise decision-making.\n\n    Telegram Notifications: Instant alerts with cheat probability sent directly to your messenger.\n\n    Flexible Punishments: Supports BAN (auto-ban) and REPORT (admin notification) modes.\n\n    GPU Acceleration: CUDA support for ultra-fast model training.\n\n    Optimized Inference: Powered by ONNX Runtime for minimal CPU overhead on the game server.\n\n🏗️ Architecture\n\nThe project is split into two components:\n\n    Java Plugin: Data collector (packet sniffer) and communication bridge.\n\n    Python Service: FastAPI-based server performing model inference and training.\n\n🛠️ Installation\n1. Java Plugin\n\n    Build the project using Maven:\n    Bash\n\n    cd plugin\n    mvn clean package\n\n    Copy target/MerluAIguard-1.0.0.jar to your server's plugins folder.\n\n2. AI Service (Python)\n\nUsing Docker (Recommended):\n\n    Ensure you have Docker and NVIDIA Container Toolkit installed (for GPU support).\n\n    Start the service:\n    Bash\n\n    docker-compose up -d\n\nManual Setup:\n\n    Install dependencies:\n    Bash\n\n    pip install -r ai_service/requirements.txt\n\n    Run the server:\n    Bash\n\n    python ai_service/main.py\n\n⚙️ Configuration\n\nAfter the first launch, edit plugins/MerluAIguard/config.yml with your settings:\n\n    python-service-url: Your Python service endpoint.\n\n    action-mode: BAN or REPORT.\n\n    telegram-token / chat-id: Your Telegram bot credentials for alerts.\n\n🧠 Training Process\n\nThe system comes without a pre-trained model, as every server environment is unique.\n\n    Data Collection:\n\n        /ai train add <player> 0 — Record legitimate gameplay.\n\n        /ai train add <player> 1 — Record gameplay using cheats.\n\n    Training:\n\n        Once enough data is collected, run /ai train start.\n\n    Activation:\n\n        After training is complete, enable protection: /ai start.\n\n📊 Feature Engineering\n\nThe system analyzes the following parameters:\n\n    delta_xyz: Movement speed and velocity.\n\n    delta_rotation: Head rotation sharpness (Yaw/Pitch).\n\n    cps: Clicks per second.\n\n    reach: Combat hit distance.\n\n    hitbox_angle: Precision of targeting.\n\n    motion_consistency: Movement smoothness and acceleration patterns.\n\n📄 License\n\nMIT License. Created by: merlusha\n\n\nRU\n# MerluAIguard 🛡️\n\n**MerluAIguard** — это современная античит-система для Minecraft Bedrock (Lumi Core/Nukkit), использующая глубокое обучение (LSTM нейросети) для анализа поведения игроков в реальном времени.\n\n## 🚀 Основные возможности\n- **Deep Learning Анализ**: Использует 3-слойную LSTM нейросеть для выявления сложных паттернов читов.\n- **Real-time Детекция**: Обработка 40-тиковых последовательностей для точного вердикта.\n- **Telegram Уведомления**: Мгновенные алерты с вероятностью чита прямо в ваш мессенджер.\n- **Гибкие Наказания**: Поддержка режимов BAN (автобан) и REPORT (уведомление администрации).\n- **GPU Ускорение**: Поддержка CUDA для сверхбыстрого обучения нейросети.\n- **Оптимизированный Инференс**: Использование ONNX Runtime для минимальной нагрузки на CPU сервера.\n\n## 🏗️ Архитектура\nПроект разделен на две части:\n1. **Java Plugin**: Сборщик данных (Data Collector) и мост связи.\n2. **Python Service**: FastAPI сервер, выполняющий инференс и обучение модели.\n\n## 🛠️ Установка\n\n### 1. Java Плагин\n1. Соберите проект через Maven:\n   ```bash\n   cd plugin\n   mvn clean package\n   ```\n2. Скопируйте `target/MerluAIguard-1.0.0.jar` в папку `plugins` вашего сервера.\n\n### 2. AI Сервис (Python)\n**Через Docker (Рекомендуется):**\n1. Убедитесь, что у вас установлен Docker и NVIDIA Container Toolkit (для GPU).\n2. Запустите сервис:\n   ```bash\n   docker-compose up -d\n   ```\n\n**Вручную:**\n1. Установите зависимости:\n   ```bash\n   pip install -r ai_service/requirements.txt\n   ```\n2. Запустите сервер:\n   ```bash\n   python ai_service/main.py\n   ```\n\n## ⚙️ Конфигурация\nПосле первого запуска в `plugins/MerluAIguard/config.yml` появятся настройки:\n- `python-service-url`: URL вашего Python сервиса.\n- `action-mode`: `BAN` или `REPORT`.\n- `telegram-token` / `chat-id`: Данные вашего бота для уведомлений.\n\n## 🧠 Процесс обучения\nСистема поставляется без предобученной модели, так как каждый сервер уникален.\n1. **Сбор данных**: \n   - `/ai train add <ник> 0` — запись легитной игры.\n   - `/ai train add <ник> 1` — запись игры с читами.\n2. **Обучение**:\n   - Когда соберете достаточно данных, пропишите `/ai train start`.\n3. **Запуск**:\n   - После завершения обучения включите защиту: `/ai start`.\n\n## 📊 Feature Engineering\nСистема анализирует следующие параметры:\n- `delta_xyz`: Скорость перемещения.\n- `delta_rotation`: Резкость поворотов головы.\n- `cps`: Кликов в секунду.\n- `reach`: Дистанция удара.\n- `hitbox_angle`: Точность наведения на цель.\n- `motion_consistency`: Плавность движений.\n\n## 📄 Лицензия\nMIT License. Автор: **merlusha**\n",
  "detection_confidence": "high",
  "downloads": 0,
  "gallery": [],
  "icon_url": "https://avatars.githubusercontent.com/u/220904984?v=4",
  "id": "merlushkaa/MerluAIguard",
  "license": {
    "id": "ARR",
    "name": "All Rights Reserved",
    "url": ""
  },
  "links": null,
  "manifest_path": "plugin/src/main/resources/plugin.yml",
  "name": "MerluAIguard",
  "primary_target": "nkx",
  "server_version": "",
  "source": "https://github.com/merlushkaa/MerluAIguard",
  "stars": 1,
  "summary": "Professional AI Anti-Cheat for Lumi Core",
  "targets": [
    "nkx",
    "nkmot"
  ],
  "updated_at": 1776333267,
  "versions": []
}